metaforge/__init__.py
metaforge/metaforge_runner.py
metaforge/cli/__init__.py
metaforge/cli/main_compare.py
metaforge/core/__init__.py
metaforge/core/base_solver.py
metaforge/problems/__init__.py
metaforge/problems/benchmark_loader.py
metaforge/problems/jobshop.py
metaforge/solvers/__init__.py
metaforge/solvers/ant_colony.py
metaforge/solvers/dqn_solver.py
metaforge/solvers/genetic_algorithm.py
metaforge/solvers/neuroevolution_solver.py
metaforge/solvers/q_learning.py
metaforge/solvers/simulated_annealing.py
metaforge/solvers/tabu_search.py
metaforge/utils/__init__.py
metaforge/utils/compare_solvers.py
metaforge/utils/plotting.py
metaforge/utils/pretty_names.py
metaforge/utils/timer.py
metaforge/utils/visualization.py
metaforge-1.0.3.dist-info/METADATA
metaforge-1.0.3.dist-info/WHEEL
metaforge-1.0.3.dist-info/top_level.txt
metaforge-1.0.3.dist-info/RECORD
