Metadata-Version: 2.4
Name: metaforge
Version: 1.0.3
Summary: MetaForge: A modular optimization framework for solving Job Shop Scheduling problems using metaheuristics and learning-based approaches.
Home-page: https://github.com/mageed-ghaleb/metaforge
Author: Mageed Ghaleb
Author-email: Mageed Ghaleb <mageed.ghaleb@gmail.com>
Project-URL: Homepage, https://github.com/mageed-ghaleb/metaforge
Project-URL: Repository, https://github.com/mageed-ghaleb/metaforge
Classifier: Topic :: Scientific/Engineering :: Artificial Intelligence
Classifier: Topic :: Scientific/Engineering :: Mathematics
Classifier: Intended Audience :: Science/Research
Classifier: Intended Audience :: Education
Classifier: Programming Language :: Python :: 3
Classifier: License :: OSI Approved :: MIT License
Requires-Python: >=3.8
Requires-Dist: numpy
Requires-Dist: matplotlib
Requires-Dist: torch
Requires-Dist: seaborn
Requires-Dist: pandas
Requires-Dist: requests
